tabular_orchestrated/__init__.py
tabular_orchestrated/components.py
tabular_orchestrated/tab_comp.py
tabular_orchestrated/dc/__init__.py
tabular_orchestrated/dc/dc_data.py
tabular_orchestrated/dc/dc_main.py
tabular_orchestrated/dc/dc_model.py
tabular_orchestrated/dc/dc_model_v2.py
tabular_orchestrated/evalml/__init__.py
tabular_orchestrated/evalml/evalml.py
tabular_orchestrated/evalml/pipeline_predict.py
tabular_orchestrated/evalml/search.py
tabular_orchestrated/evalml/select_pipeline.py
tabular_orchestrated/evalml/analysis/__init__.py
tabular_orchestrated/evalml/analysis/analysis_comp.py
tabular_orchestrated/evalml/analysis/analysis_comp_v2.py
tabular_orchestrated/evalml/analysis/utils.py
tabular_orchestrated/mljar/__init__.py
tabular_orchestrated/mljar/mljar.py
tabular_orchestrated_kfp/__init__.py
tabular_orchestrated_kfp/gcp.py
tabular_orchestrated-0.5.1b0.dist-info/METADATA
tabular_orchestrated-0.5.1b0.dist-info/WHEEL
tabular_orchestrated-0.5.1b0.dist-info/licenses/LICENSE
tabular_orchestrated-0.5.1b0.dist-info/RECORD
